<annotation>
	<folder>JPEGImages</folder>
	<filename>img1503.JPG</filename>
	<path>C:\Users\user\Downloads\tensorflow_yolo_v3-master\tensorflow_yolo_v3-master\training_data\images\JPEGImages\img1503.JPG</path>
	<source>
		<database>Unknown</database>
	</source>
	<size>
		<width>1608</width>
		<height>681</height>
		<depth>3</depth>
	</size>
	<segmented>0</segmented>
	<object>
		<name>buy</name>
		<pose>Unspecified</pose>
		<truncated>0</truncated>
		<difficult>0</difficult>
		<bndbox>
			<xmin>197</xmin>
			<ymin>302</ymin>
			<xmax>410</xmax>
			<ymax>641</ymax>
		</bndbox>
	</object>
	<object>
		<name>buy</name>
		<pose>Unspecified</pose>
		<truncated>0</truncated>
		<difficult>0</difficult>
		<bndbox>
			<xmin>611</xmin>
			<ymin>138</ymin>
			<xmax>736</xmax>
			<ymax>306</ymax>
		</bndbox>
	</object>
	<object>
		<name>buy</name>
		<pose>Unspecified</pose>
		<truncated>0</truncated>
		<difficult>0</difficult>
		<bndbox>
			<xmin>1270</xmin>
			<ymin>156</ymin>
			<xmax>1450</xmax>
			<ymax>236</ymax>
		</bndbox>
	</object>
</annotation>
