<annotation>
	<folder>JPEGImages</folder>
	<filename>img253.JPG</filename>
	<path>C:\Users\user\Downloads\tensorflow_yolo_v3-master\tensorflow_yolo_v3-master\training_data\images\JPEGImages\img253.JPG</path>
	<source>
		<database>Unknown</database>
	</source>
	<size>
		<width>1661</width>
		<height>398</height>
		<depth>3</depth>
	</size>
	<segmented>0</segmented>
	<object>
		<name>buy</name>
		<pose>Unspecified</pose>
		<truncated>0</truncated>
		<difficult>0</difficult>
		<bndbox>
			<xmin>244</xmin>
			<ymin>267</ymin>
			<xmax>355</xmax>
			<ymax>357</ymax>
		</bndbox>
	</object>
	<object>
		<name>buy</name>
		<pose>Unspecified</pose>
		<truncated>0</truncated>
		<difficult>0</difficult>
		<bndbox>
			<xmin>4</xmin>
			<ymin>216</ymin>
			<xmax>119</xmax>
			<ymax>374</ymax>
		</bndbox>
	</object>
	<object>
		<name>buy</name>
		<pose>Unspecified</pose>
		<truncated>0</truncated>
		<difficult>0</difficult>
		<bndbox>
			<xmin>673</xmin>
			<ymin>191</ymin>
			<xmax>731</xmax>
			<ymax>280</ymax>
		</bndbox>
	</object>
	<object>
		<name>sell</name>
		<pose>Unspecified</pose>
		<truncated>0</truncated>
		<difficult>0</difficult>
		<bndbox>
			<xmin>786</xmin>
			<ymin>38</ymin>
			<xmax>844</xmax>
			<ymax>141</ymax>
		</bndbox>
	</object>
</annotation>
