<annotation>
	<folder>JPEGImages</folder>
	<filename>img563.JPG</filename>
	<path>C:\Users\user\Downloads\tensorflow_yolo_v3-master\tensorflow_yolo_v3-master\training_data\images\JPEGImages\img563.JPG</path>
	<source>
		<database>Unknown</database>
	</source>
	<size>
		<width>1757</width>
		<height>628</height>
		<depth>3</depth>
	</size>
	<segmented>0</segmented>
	<object>
		<name>sell</name>
		<pose>Unspecified</pose>
		<truncated>0</truncated>
		<difficult>0</difficult>
		<bndbox>
			<xmin>1272</xmin>
			<ymin>143</ymin>
			<xmax>1543</xmax>
			<ymax>247</ymax>
		</bndbox>
	</object>
	<object>
		<name>sell</name>
		<pose>Unspecified</pose>
		<truncated>0</truncated>
		<difficult>0</difficult>
		<bndbox>
			<xmin>1555</xmin>
			<ymin>196</ymin>
			<xmax>1690</xmax>
			<ymax>307</ymax>
		</bndbox>
	</object>
</annotation>
