<annotation>
	<folder>JPEGImages</folder>
	<filename>img923.JPG</filename>
	<path>C:\Users\user\Downloads\tensorflow_yolo_v3-master\tensorflow_yolo_v3-master\training_data\images\JPEGImages\img923.JPG</path>
	<source>
		<database>Unknown</database>
	</source>
	<size>
		<width>1786</width>
		<height>666</height>
		<depth>3</depth>
	</size>
	<segmented>0</segmented>
	<object>
		<name>sell</name>
		<pose>Unspecified</pose>
		<truncated>0</truncated>
		<difficult>0</difficult>
		<bndbox>
			<xmin>592</xmin>
			<ymin>347</ymin>
			<xmax>936</xmax>
			<ymax>439</ymax>
		</bndbox>
	</object>
</annotation>
